ai_lifecycle_cli/__init__.py
ai_lifecycle_cli/main.py
ai_lifecycle_cli/lib/__init__.py
ai_lifecycle_cli/lib/actions/__init__.py
ai_lifecycle_cli/lib/actions/export_wml_assets.py
ai_lifecycle_cli/lib/actions/export_wml_assets_v25.py
ai_lifecycle_cli/lib/actions/import_wml_assets.py
ai_lifecycle_cli/lib/actions/import_wml_assets_v25.py
ai_lifecycle_cli/lib/actions/manage_wml_assets.py
ai_lifecycle_cli/lib/actions/manage_wml_deployment_jobs.py
ai_lifecycle_cli/lib/actions/manage_wml_deployments.py
ai_lifecycle_cli/lib/actions/manage_wml_spaces.py
ai_lifecycle_cli/lib/actions/preparation.py
ai_lifecycle_cli/lib/actions/translate_assets.py
ai_lifecycle_cli/lib/clients/__init__.py
ai_lifecycle_cli/lib/clients/git_client.py
ai_lifecycle_cli/lib/clients/rest_client.py
ai_lifecycle_cli/lib/commands/__init__.py
ai_lifecycle_cli/lib/commands/asset_command.py
ai_lifecycle_cli/lib/commands/deployment_command.py
ai_lifecycle_cli/lib/commands/deployment_job_command.py
ai_lifecycle_cli/lib/commands/export_command.py
ai_lifecycle_cli/lib/commands/import_command.py
ai_lifecycle_cli/lib/commands/space_command.py
ai_lifecycle_cli/lib/resources/wml_model.json
ai_lifecycle_cli/lib/resources/wml_pipeline.json
ai_lifecycle_cli/lib/utils/AuthHandler.py
ai_lifecycle_cli/lib/utils/CPDStatusHandler.py
ai_lifecycle_cli/lib/utils/Constants.py
ai_lifecycle_cli/lib/utils/FsHandler.py
ai_lifecycle_cli/lib/utils/LoggingHandler.py
ai_lifecycle_cli/lib/utils/print_utils.py
ai_lifecycle_cli-1.0.0.dist-info/LICENSE
ai_lifecycle_cli-1.0.0.dist-info/METADATA
ai_lifecycle_cli-1.0.0.dist-info/WHEEL
ai_lifecycle_cli-1.0.0.dist-info/entry_points.txt
ai_lifecycle_cli-1.0.0.dist-info/top_level.txt
ai_lifecycle_cli-1.0.0.dist-info/zip-safe
ai_lifecycle_cli-1.0.0.dist-info/RECORD
