Metadata-Version: 2.1
Name: ai-lifecycle-cli
Version: 1.0.0
Summary: CLI library for importing, exporting and managing IBM Watson Machine Learning assets.
Home-page: https://www.ibm.com/cloud/machine-learning
Author: IBM Corp
Author-email: daniel.ryszka@pl.ibm.com
License: Apache-2.0
Keywords: watson-machine-learning,watson-studio,ibm-watson
Platform: UNKNOWN
Classifier: Programming Language :: Python
Classifier: Programming Language :: Python :: 3
Classifier: Intended Audience :: Developers
Classifier: Intended Audience :: Science/Research
Classifier: Operating System :: OS Independent
Classifier: Topic :: Software Development :: Libraries :: Python Modules
Classifier: Topic :: Software Development :: Libraries :: Application Frameworks
Requires-Python: >=3.5
Requires-Dist: urllib3 (==1.25.8)
Requires-Dist: jmespath (==0.9.4)
Requires-Dist: requests (==2.22.0)
Requires-Dist: flatten-dict (==0.2.0)
Requires-Dist: PyGithub (==1.46)
Requires-Dist: PyJWT (==1.7.1)
